craft_archives/__init__.py
craft_archives/_version.py
craft_archives/defaults.py
craft_archives/errors.py
craft_archives/py.typed
craft_archives/utils.py
craft_archives/repo/__init__.py
craft_archives/repo/apt_key_manager.py
craft_archives/repo/apt_ppa.py
craft_archives/repo/apt_preferences_manager.py
craft_archives/repo/apt_sources_manager.py
craft_archives/repo/apt_uca.py
craft_archives/repo/errors.py
craft_archives/repo/gpg.py
craft_archives/repo/installer.py
craft_archives/repo/package_repository.py
craft_archives/repo/projects.py
craft_archives-2.2.0.dist-info/licenses/LICENSE
craft_archives-2.2.0.dist-info/METADATA
craft_archives-2.2.0.dist-info/WHEEL
craft_archives-2.2.0.dist-info/top_level.txt
craft_archives-2.2.0.dist-info/RECORD
