Metadata-Version: 2.4
Name: craft_archives
Version: 2.2.0
License-Expression: LGPL-3.0-or-later
Classifier: Development Status :: 5 - Production/Stable
Classifier: Operating System :: POSIX :: Linux
Classifier: Programming Language :: Python :: 3
Classifier: Programming Language :: Python :: 3.10
Classifier: Programming Language :: Python :: 3.11
Classifier: Programming Language :: Python :: 3.12
Classifier: Topic :: Software Development :: Libraries
Classifier: Topic :: Software Development :: Libraries :: Python Modules
Classifier: Topic :: System :: Archiving :: Packaging
Requires-Python: >=3.10
License-File: LICENSE
Requires-Dist: distro>=1.3.0
Requires-Dist: launchpadlib>=1.11
Requires-Dist: lazr.restfulclient>=0.14.4
Requires-Dist: lazr.uri>=1.0.6
Requires-Dist: overrides>=6.0
Requires-Dist: pydantic~=2.7
Requires-Dist: python-debian==1.0.1
Dynamic: license-file
